amaze_dict/__init__.py
amaze_dict/amaze_dict.py
amaze_dict-0.0.4.dist-info/METADATA
amaze_dict-0.0.4.dist-info/WHEEL
amaze_dict-0.0.4.dist-info/top_level.txt
amaze_dict-0.0.4.dist-info/RECORD
