Metadata-Version: 2.1
Name: amaze-dict
Version: 0.0.4
Summary: 一个便捷的访问多层级dict的方法
Home-page: https://github.com/chenglp1215/amaze_dict
Author: chenglp
Author-email: chenglp1215@163.com
License: UNKNOWN
Platform: UNKNOWN
Classifier: Programming Language :: Python :: 3
Classifier: License :: OSI Approved :: MIT License
Classifier: Operating System :: OS Independent
Requires-Python: >=3.6
